pyronounce/__init__.py
pyronounce/cli.py
pyronounce/core.py
pyronounce/model.py
pyronounce/utils.py
pyronounce/data/README.md
pyronounce/data/default_model.pkl
pyronounce-0.1.2.dist-info/METADATA
pyronounce-0.1.2.dist-info/WHEEL
pyronounce-0.1.2.dist-info/entry_points.txt
pyronounce-0.1.2.dist-info/licenses/LICENSE
pyronounce-0.1.2.dist-info/RECORD
