Metadata-Version: 2.4
Name: pyronounce
Version: 0.1.2
Summary: Package to assess the pronounceability of English words and text.
Author-email: Yasar Kocal <uyasarkocal+pypi@gmail.com>
License: MIT
License-File: LICENSE
Requires-Python: >=3.7
Requires-Dist: click
Requires-Dist: numpy>=1.22.0
Requires-Dist: scikit-learn
Requires-Dist: scipy
Provides-Extra: dev
Requires-Dist: black; extra == 'dev'
Requires-Dist: isort; extra == 'dev'
Requires-Dist: pytest; extra == 'dev'
Provides-Extra: nltk
Requires-Dist: nltk>=3.8.0; extra == 'nltk'
